fastflows/__init__.py
fastflows/cli/__init__.py
fastflows/cli/flow_runs.py
fastflows/cli/flows.py
fastflows/cli/main.py
fastflows/cli/task_runs.py
fastflows/cli/utils.py
fastflows/config/app.py
fastflows/config/auth.py
fastflows/config/logging.py
fastflows/core/blocks.py
fastflows/core/catalog/__init__.py
fastflows/core/catalog/cache.py
fastflows/core/catalog/catalog.py
fastflows/core/catalog/reader.py
fastflows/core/catalog/storage.py
fastflows/core/deployment.py
fastflows/core/flow.py
fastflows/core/flow_run.py
fastflows/core/storage.py
fastflows/core/task_run.py
fastflows/core/utils/parse_data.py
fastflows/core/utils/singleton.py
fastflows/errors.py
fastflows/main.py
fastflows/providers/__init__.py
fastflows/providers/base.py
fastflows/providers/prefect.py
fastflows/providers/utils.py
fastflows/routers/__init__.py
fastflows/routers/flow_runs.py
fastflows/routers/flows.py
fastflows/routers/task_runs.py
fastflows/routers/utils.py
fastflows/schemas/__init__.py
fastflows/schemas/logging.py
fastflows/schemas/prefect/__init__.py
fastflows/schemas/prefect/block.py
fastflows/schemas/prefect/deployment.py
fastflows/schemas/prefect/flow.py
fastflows/schemas/prefect/flow_data.py
fastflows/schemas/prefect/flow_run.py
fastflows/schemas/prefect/misc.py
fastflows/schemas/prefect/task_run.py
fastflows/utils/__init__.py
fastflows/utils/app_exceptions.py
fastflows/utils/core.py
fastflows/utils/get_list_of_app_exceptions_for_frontend.py
fastflows/utils/request_exceptions.py
fastflows/utils/service_result.py
fastflows-0.1.2.dist-info/entry_points.txt
fastflows-0.1.2.dist-info/LICENSE
fastflows-0.1.2.dist-info/WHEEL
fastflows-0.1.2.dist-info/METADATA
fastflows-0.1.2.dist-info/RECORD
