Metadata-Version: 2.1
Name: fastflows
Version: 0.1.2
Summary: FastFlows is a FastAPI server & command line tool to comunicate with Prefect 2.0 as a Workflow manager (and in future other systems like Pygeoapi, for example) to deploy, run, track flows and more.
Home-page: https://github.com/geobeyond/fastflows
License: MIT
Author: Francesco Bartoli
Author-email: francesco.bartoli@geobeyond.it
Requires-Python: >=3.8,<4.0
Classifier: Development Status :: 1 - Planning
Classifier: License :: OSI Approved :: MIT License
Classifier: Programming Language :: Python :: 3
Classifier: Programming Language :: Python :: 3.8
Classifier: Programming Language :: Python :: 3.9
Classifier: Programming Language :: Python :: 3.10
Requires-Dist: fastapi-opa (>=1.3.7,<2.0.0)
Requires-Dist: fsspec (>=2022.7.1,<2023.0.0)
Requires-Dist: httpx (>=0.23.0,<0.24.0)
Requires-Dist: loguru (>=0.6.0,<0.7.0)
Requires-Dist: mangum (>=0.15.0,<0.16.0)
Requires-Dist: pydantic[dotenv] (>=1.9.1,<2.0.0)
Requires-Dist: python-slugify (>=6.1.2,<7.0.0)
Requires-Dist: rich (>=12.4.4,<13.0.0)
Requires-Dist: s3fs (>=2022.7.1,<2023.0.0)
Requires-Dist: typer (>=0.6.1,<0.7.0)
Requires-Dist: uvicorn (>=0.17.6,<0.19.0)
Project-URL: Documentation, https://github.com/geobeyond/fastflows
Project-URL: Repository, https://github.com/geobeyond/fastflows
